renovosolutions_aurora_native_backup/__init__.py
renovosolutions_aurora_native_backup/py.typed
renovosolutions_aurora_native_backup/_jsii/__init__.py
renovosolutions_aurora_native_backup/_jsii/cdk-library-aurora-native-backup@0.1.1.jsii.tgz
renovosolutions_aws_cdk_aurora_native_backup-0.1.1.dist-info/LICENSE
renovosolutions_aws_cdk_aurora_native_backup-0.1.1.dist-info/METADATA
renovosolutions_aws_cdk_aurora_native_backup-0.1.1.dist-info/WHEEL
renovosolutions_aws_cdk_aurora_native_backup-0.1.1.dist-info/top_level.txt
renovosolutions_aws_cdk_aurora_native_backup-0.1.1.dist-info/RECORD
