Metadata-Version: 2.1
Name: renovosolutions.aws-cdk-aurora-native-backup
Version: 0.1.1
Summary: AWS CDK construct library for Aurora backup and restore using ECS on a schedule, storing backups in S3.
Home-page: https://github.com/RenovoSolutions/cdk-library-aurora-native-backup.git
Author: Renovo Solutions<webmaster+cdk@renovo1.com>
License: Apache-2.0
Project-URL: Source, https://github.com/RenovoSolutions/cdk-library-aurora-native-backup.git
Classifier: Intended Audience :: Developers
Classifier: Operating System :: OS Independent
Classifier: Programming Language :: JavaScript
Classifier: Programming Language :: Python :: 3 :: Only
Classifier: Programming Language :: Python :: 3.9
Classifier: Programming Language :: Python :: 3.10
Classifier: Programming Language :: Python :: 3.11
Classifier: Typing :: Typed
Classifier: Development Status :: 5 - Production/Stable
Classifier: License :: OSI Approved
Requires-Python: ~=3.9
License-File: LICENSE
Requires-Dist: aws-cdk-lib <3.0.0,>=2.233.0
Requires-Dist: cdk-ecr-deployment <5.0.0,>=4.0.5
Requires-Dist: cdk-nag ==2.37.55
Requires-Dist: constructs <11.0.0,>=10.0.5
Requires-Dist: jsii <2.0.0,>=1.125.0
Requires-Dist: publication >=0.0.3
Requires-Dist: typeguard ==2.13.3
